omicron_gap/Gwf.py
omicron_gap/Omicrondag.py
omicron_gap/__init__.py
omicron_gap/_version.py
omicron_gap/batch_merge_dir.py
omicron_gap/clean_logs.py
omicron_gap/compare_dirs.py
omicron_gap/condor_get_env.py
omicron_gap/dqseg_print.py
omicron_gap/find_gaps.py
omicron_gap/framelatency.py
omicron_gap/gap-print.py
omicron_gap/gap_analysis.py
omicron_gap/gap_handler.py
omicron_gap/gap_plot_animator.py
omicron_gap/gap_plotter.py
omicron_gap/gap_subdag_create.py
omicron_gap/gap_utils.py
omicron_gap/gwf_functions.py
omicron_gap/latest_frame.py
omicron_gap/logfile_backup.py
omicron_gap/merge_metric_days.py
omicron_gap/merge_omicron.py
omicron_gap/metric_day_merge.py
omicron_gap/monitor_crondor_jobs.py
omicron_gap/omicron_channel_check.py
omicron_gap/plot_log_scrapings.py
omicron_gap/pyomicron_log.py
omicron_gap/pyomicron_log_scanner.py
omicron_gap/seg_txt_print.py
omicron_gap/special_run.py
omicron_gap/trigger_backup_interval.py
omicron_gap/trigger_plot.py
omicron_gap/tst-auth.py
omicron_gap-0.0.56.dist-info/licenses/LICENSE
omicron_gap-0.0.56.dist-info/METADATA
omicron_gap-0.0.56.dist-info/WHEEL
omicron_gap-0.0.56.dist-info/entry_points.txt
omicron_gap-0.0.56.dist-info/top_level.txt
omicron_gap-0.0.56.dist-info/RECORD
